itpe/__init__.py
itpe/dreamwidth.py
itpe-2016.0.dist-info/DESCRIPTION.rst
itpe-2016.0.dist-info/entry_points.txt
itpe-2016.0.dist-info/METADATA
itpe-2016.0.dist-info/metadata.json
itpe-2016.0.dist-info/RECORD
itpe-2016.0.dist-info/top_level.txt
itpe-2016.0.dist-info/WHEEL
