Metadata-Version: 2.0
Name: itpe
Version: 2016.0
Summary: Scripts for generating the master post for ITPE (the Informal Twitter Podfic Exchange)
Home-page: https://github.com/alexwlchan/itpe
Author: Alex Chan
Author-email: alex@alexwlchan.net
License: MIT
Platform: UNKNOWN
Classifier: Development Status :: 5 - Production/Stable
Classifier: Intended Audience :: Other Audience
Classifier: License :: OSI Approved :: MIT License
Classifier: Programming Language :: Python :: 2
Classifier: Programming Language :: Python :: 2.7
Classifier: Programming Language :: Python :: 3
Classifier: Programming Language :: Python :: 3.3
Classifier: Programming Language :: Python :: 3.4
Classifier: Programming Language :: Python :: 3.5
Requires-Dist: docopt
Requires-Dist: jinja2
Requires-Dist: termcolor
